bgmiget/__init__.py
bgmiget/bgmiget.py
bgmiget/persistentdict.py
bgmiget/result.py
bgmiget/sources/__init__.py
bgmiget/sources/mikanproject.py
bgmiget-1.0.5.dist-info/METADATA
bgmiget-1.0.5.dist-info/WHEEL
bgmiget-1.0.5.dist-info/entry_points.txt
bgmiget-1.0.5.dist-info/RECORD
