Metadata-Version: 2.1
Name: bgmiget
Version: 1.0.5
Summary: a way to download anime.
Author: aoout
Author-email: wuz66280@gmail.com
Requires-Python: >=3.8,<4.0
Classifier: Programming Language :: Python :: 3
Classifier: Programming Language :: Python :: 3.8
Classifier: Programming Language :: Python :: 3.9
Classifier: Programming Language :: Python :: 3.10
Classifier: Programming Language :: Python :: 3.11
Classifier: Programming Language :: Python :: 3.12
Classifier: Programming Language :: Python :: 3.13
Requires-Dist: beautifulsoup4 (>=4.11.1,<5.0.0)
Requires-Dist: fire (>=0.4.0,<0.5.0)
Requires-Dist: requests (>=2.28.1,<3.0.0)
Requires-Dist: torrentp (>=0.1.5,<0.2.0)
